stirfried/__init__.py
stirfried/celery.py
stirfried/server.py
stirfried-0.7.0.dist-info/WHEEL
stirfried-0.7.0.dist-info/METADATA
stirfried-0.7.0.dist-info/RECORD
