Metadata-Version: 2.1
Name: stirfried
Version: 0.7.0
Summary: Socket.IO server to schedule Celery tasks from clients in real-time.
License: MIT
Author: Korijn van Golen
Author-email: korijn@gmail.com
Requires-Python: >=3.6,<4.0
Classifier: License :: OSI Approved :: MIT License
Classifier: Programming Language :: Python :: 3
Classifier: Programming Language :: Python :: 3.6
Classifier: Programming Language :: Python :: 3.7
Classifier: Programming Language :: Python :: 3.8
Provides-Extra: msgpack
Provides-Extra: server
Requires-Dist: aioredis (>=1.3.1,<2.0.0); extra == "server"
Requires-Dist: celery (>=4.4.0,<5.0.0)
Requires-Dist: msgpack-python (>=0.5.6,<0.6.0); extra == "msgpack"
Requires-Dist: python-socketio (>=4.4.0,<5.0.0)
Requires-Dist: redis (>=3.4.1,<4.0.0)
Requires-Dist: starlette (>=0.13.2,<0.14.0); extra == "server"
Requires-Dist: uvicorn (>=0.11.3,<0.12.0); extra == "server"
